byted_overpass_content_tcs_openapi/__init__.py
byted_overpass_content_tcs_openapi-0.0.1.dist-info/METADATA
byted_overpass_content_tcs_openapi-0.0.1.dist-info/WHEEL
byted_overpass_content_tcs_openapi-0.0.1.dist-info/top_level.txt
byted_overpass_content_tcs_openapi-0.0.1.dist-info/RECORD
